datmat/__init__.py
datmat/exceptions.py
datmat/helpers.py
datmat/ioplugin.py
datmat/models.py
datmat/typehints.py
datmat/cli/__init__.py
datmat/plugins/__init__.py
datmat/plugins/eucaim.py
datmat/plugins/eucaimres.py
datmat/plugins/filesystem.py
datmat/plugins/structureddirectory.py
datmat/plugins/xnatstorage.py
datmat-0.2.0.dist-info/licenses/LICENSE
datmat-0.2.0.dist-info/METADATA
datmat-0.2.0.dist-info/WHEEL
datmat-0.2.0.dist-info/entry_points.txt
datmat-0.2.0.dist-info/top_level.txt
datmat-0.2.0.dist-info/RECORD
