Metadata-Version: 2.4
Name: datmat
Version: 0.2.0
Summary: Datmat is a tool for data materalisation; it gets your data where it is, to where you need it to be.
Home-page: https://gitlab.com/radiology/infrastructure/data-materialisation
Author: H.C. Achterberg, M. Koek, A. Versteeg, M. Birhanu, A.G.J. Harms, I. Bocharov
Author-email: h.achterberg@erasmusmc.nl, m.koek@erasmusmc.nl, a.versteeg@erasmusmc.nl, m.birhanu@erasmusmc.nl
License: Apache 2.0
Project-URL: Documentation, https://datmat.readthedocs.io
Project-URL: Issues, https://gitlab.com/radiology/infrastructure/data-materialisation/-/issues
Project-URL: Download, https://gitlab.com/radiology/infrastructure/data-materialisation/-/archive/master/data-materialisation-master.zip
Project-URL: CI/CD, https://gitlab.com/radiology/infrastructure/data-materialisation/-/pipelines
Classifier: Development Status :: 4 - Beta
Classifier: Intended Audience :: Developers
Classifier: Intended Audience :: Science/Research
Classifier: Intended Audience :: Healthcare Industry
Classifier: Intended Audience :: Information Technology
Classifier: Intended Audience :: Education
Classifier: License :: OSI Approved :: Apache Software License
Classifier: Natural Language :: English
Classifier: Operating System :: OS Independent
Classifier: Programming Language :: Python :: 3.8
Classifier: Programming Language :: Python :: 3.9
Classifier: Programming Language :: Python :: 3.10
Classifier: Programming Language :: Python :: 3.11
Classifier: Programming Language :: Python :: 3 :: Only
Classifier: Topic :: Scientific/Engineering :: Information Analysis
Classifier: Topic :: System :: Logging
Classifier: Topic :: Utilities
License-File: LICENSE
Requires-Dist: click==8.1.7
Requires-Dist: requests>=2.13.0
Requires-Dist: xnat>=0.6.1
Requires-Dist: yarl>=1.7.0
Requires-Dist: pydantic~=2.7.1
Dynamic: author
Dynamic: author-email
Dynamic: classifier
Dynamic: description
Dynamic: description-content-type
Dynamic: home-page
Dynamic: license
Dynamic: license-file
Dynamic: project-url
Dynamic: requires-dist
Dynamic: summary
